wmutil-0.3.0.dist-info/METADATA
wmutil-0.3.0.dist-info/WHEEL
wmutil-0.3.0.dist-info/licenses/LICENSE
wmutil/__init__.py
wmutil/__init__.pyi
wmutil/py.typed
wmutil/wmutil.cp313-win_amd64.pyd
wmutil-0.3.0.dist-info/RECORD
